{
	"name": "greenpeace/planet4-test-proteus",
	"description": "Greenpeace P4 test-proteus",
	"license": "MIT",
	"require": {
		"greenpeace/planet4-master-theme": "7",
		"greenpeace/planet4-plugin-gutenberg-blocks": "7"
	},
	"scripts": {
		"site:custom": []
	},
	"repositories": [
		{
			"type": "package",
			"package": {
				"name": "greenpeace/planet4-plugin-gutenberg-blocks",
				"type": "wordpress-plugin",
				"autoload": null,
				"extra": null,
				"version": 7,
				"dist": {
					"type": "zip",
					"url": "https://storage.googleapis.com/planet4-packages/planet4-plugin-gutenberg-blocks/be5ecdaedec6f0cf29272f4910105c371da4b3a8.zip"
				}
			}
		},
		{
			"type": "package",
			"package": {
				"name": "greenpeace/planet4-master-theme",
				"type": "wordpress-theme",
				"autoload": {
					"psr-4": {
						"P4\\MasterTheme\\": "src/"
					}
				},
				"extra": {
					"installer-paths": {
						"vendor/plugins/{$name}/": [
							"type:wordpress-plugin"
						]
					}
				},
				"version": 7,
				"dist": {
					"type": "zip",
					"url": "https://storage.googleapis.com/planet4-packages/planet4-master-theme/b0f775687f5b9cd6c8f01a85bb8511963af2ad1c.zip"
				}
			}
		}
	]
}
